[{"id":0,"url":"/musicvideo.php?vid=87b7129b0"},{"id":1,"url":"/musicvideo.php?vid=e0589f7ea"},{"id":2,"url":"/musicvideo.php?vid=6f8631438"},{"id":3,"url":"/musicvideo.php?vid=4a729df62"},{"id":4,"url":"/musicvideo.php?vid=b250651f0"},{"id":5,"url":"/musicvideo.php?vid=245ad19d4"},{"id":6,"url":"/musicvideo.php?vid=91e068f4d"},{"id":7,"url":"/musicvideo.php?vid=894c781f3"},{"id":8,"url":"/musicvideo.php?vid=9eedc07ca"},{"id":9,"url":"/musicvideo.php?vid=1737bd31e"},{"id":10,"url":"/musicvideo.php?vid=a8598e871"},{"id":11,"url":"/musicvideo.php?vid=46dff4a30"},{"id":12,"url":"/musicvideo.php?vid=70930bb31"},{"id":13,"url":"/musicvideo.php?vid=fb3e40a8b"},{"id":14,"url":"/musicvideo.php?vid=d2738a700"},{"id":15,"url":"/musicvideo.php?vid=b5db12f01"},{"id":16,"url":"/musicvideo.php?vid=3183f349a"},{"id":17,"url":"/musicvideo.php?vid=ebe180d81"},{"id":18,"url":"/musicvideo.php?vid=d954db45d"},{"id":19,"url":"/musicvideo.php?vid=2715139ee"},{"id":20,"url":"/musicvideo.php?vid=39cfa446a"},{"id":21,"url":"/musicvideo.php?vid=4f7136d68"},{"id":22,"url":"/musicvideo.php?vid=d1087d7b3"},{"id":23,"url":"/musicvideo.php?vid=b62ef2444"},{"id":24,"url":"/musicvideo.php?vid=355015b0d"},{"id":25,"url":"/musicvideo.php?vid=440b4bd21"},{"id":26,"url":"/musicvideo.php?vid=437f245f8"},{"id":27,"url":"/musicvideo.php?vid=8b46700c5"},{"id":28,"url":"/musicvideo.php?vid=11657fa75"},{"id":29,"url":"/musicvideo.php?vid=0a63a56d2"},{"id":30,"url":"/musicvideo.php?vid=e9b2d51b4"},{"id":31,"url":"/musicvideo.php?vid=efb43fa53"},{"id":32,"url":"/musicvideo.php?vid=653596386"},{"id":33,"url":"/musicvideo.php?vid=ef75ffd4c"},{"id":34,"url":"/musicvideo.php?vid=87e1fe5f2"},{"id":35,"url":"/musicvideo.php?vid=6763de809"},{"id":36,"url":"/musicvideo.php?vid=716819b18"},{"id":37,"url":"/musicvideo.php?vid=bea672b57"},{"id":38,"url":"/musicvideo.php?vid=1adab11a9"},{"id":39,"url":"/musicvideo.php?vid=64a3adb8f"},{"id":40,"url":"/musicvideo.php?vid=61d4ac742"},{"id":41,"url":"/musicvideo.php?vid=8ae02ae69"},{"id":42,"url":"/musicvideo.php?vid=7e660d8da"},{"id":43,"url":"/musicvideo.php?vid=055717561"},{"id":44,"url":"/musicvideo.php?vid=e3dd881a2"},{"id":45,"url":"/musicvideo.php?vid=5155a6782"},{"id":46,"url":"/musicvideo.php?vid=c8e789f16"},{"id":47,"url":"/musicvideo.php?vid=d5805426b"},{"id":48,"url":"/musicvideo.php?vid=1011df549"},{"id":49,"url":"/musicvideo.php?vid=07d40624c"},{"id":50,"url":"/musicvideo.php?vid=83aec6ec1"},{"id":51,"url":"/musicvideo.php?vid=2b8d9f8b2"},{"id":52,"url":"/musicvideo.php?vid=880d4f260"},{"id":53,"url":"/musicvideo.php?vid=c7c1530b6"},{"id":54,"url":"/musicvideo.php?vid=d218db53b"},{"id":55,"url":"/musicvideo.php?vid=0e6bc371a"},{"id":56,"url":"/musicvideo.php?vid=f0ca1ba43"},{"id":57,"url":"/musicvideo.php?vid=8c5dd74ad"},{"id":58,"url":"/musicvideo.php?vid=9ec57888a"},{"id":59,"url":"/musicvideo.php?vid=47fd89d72"},{"id":60,"url":"/musicvideo.php?vid=5db91751c"},{"id":61,"url":"/musicvideo.php?vid=f8fae22bb"},{"id":62,"url":"/musicvideo.php?vid=de835e7a7"},{"id":63,"url":"/musicvideo.php?vid=0092327be"},{"id":64,"url":"/musicvideo.php?vid=55307740a"},{"id":65,"url":"/musicvideo.php?vid=6a0d3ba9a"},{"id":66,"url":"/musicvideo.php?vid=480d61b6a"},{"id":67,"url":"/musicvideo.php?vid=9b74c8059"},{"id":68,"url":"/musicvideo.php?vid=ec6e2b906"},{"id":69,"url":"/musicvideo.php?vid=5b7a542f6"},{"id":70,"url":"/musicvideo.php?vid=f551e4886"},{"id":71,"url":"/musicvideo.php?vid=507682939"},{"id":72,"url":"/musicvideo.php?vid=aa4c50362"},{"id":73,"url":"/musicvideo.php?vid=264329e49"},{"id":74,"url":"/musicvideo.php?vid=07da8c78c"},{"id":75,"url":"/musicvideo.php?vid=f180643dc"},{"id":76,"url":"/musicvideo.php?vid=9dde60604"},{"id":77,"url":"/musicvideo.php?vid=37e2f6e54"},{"id":78,"url":"/musicvideo.php?vid=6eb1329e5"},{"id":79,"url":"/musicvideo.php?vid=9ffd78f38"},{"id":80,"url":"/musicvideo.php?vid=0f4f6641a"},{"id":81,"url":"/musicvideo.php?vid=02113d249"},{"id":82,"url":"/musicvideo.php?vid=4afe3ea1f"},{"id":83,"url":"/musicvideo.php?vid=faf529243"},{"id":84,"url":"/musicvideo.php?vid=5ce0e3353"},{"id":85,"url":"/musicvideo.php?vid=cc6c2206e"},{"id":86,"url":"/musicvideo.php?vid=f11f5ed09"},{"id":87,"url":"/musicvideo.php?vid=6beac2ab7"},{"id":88,"url":"/musicvideo.php?vid=7df9bfd0a"},{"id":89,"url":"/musicvideo.php?vid=1a46874c4"},{"id":90,"url":"/musicvideo.php?vid=c01f737ed"},{"id":91,"url":"/musicvideo.php?vid=b62fd4557"},{"id":92,"url":"/musicvideo.php?vid=efa6b4f98"},{"id":93,"url":"/musicvideo.php?vid=a477e8fe5"},{"id":94,"url":"/musicvideo.php?vid=fa1bfdd87"},{"id":95,"url":"/musicvideo.php?vid=e8e4c1d41"},{"id":96,"url":"/musicvideo.php?vid=7acdeeaa2"},{"id":97,"url":"/musicvideo.php?vid=c13be36af"},{"id":98,"url":"/musicvideo.php?vid=d5ee1110e"},{"id":99,"url":"/musicvideo.php?vid=c714ac7cd"},{"id":100,"url":"/musicvideo.php?vid=875b5c0b7"},{"id":101,"url":"/musicvideo.php?vid=bd03f8f25"},{"id":102,"url":"/musicvideo.php?vid=2a108c5c1"},{"id":103,"url":"/musicvideo.php?vid=8b5759f3c"},{"id":104,"url":"/musicvideo.php?vid=7b10200bf"},{"id":105,"url":"/musicvideo.php?vid=4d2310e67"},{"id":106,"url":"/musicvideo.php?vid=625cbfacb"},{"id":107,"url":"/musicvideo.php?vid=7433b900b"},{"id":108,"url":"/musicvideo.php?vid=4fc0484a5"},{"id":109,"url":"/musicvideo.php?vid=dcb39ad40"},{"id":110,"url":"/musicvideo.php?vid=c83a1495b"},{"id":111,"url":"/musicvideo.php?vid=b3d0862c8"},{"id":112,"url":"/musicvideo.php?vid=313494045"},{"id":113,"url":"/musicvideo.php?vid=a0c1ee9d5"},{"id":114,"url":"/musicvideo.php?vid=4145890cb"},{"id":115,"url":"/musicvideo.php?vid=0244a6e10"},{"id":116,"url":"/musicvideo.php?vid=422652021"},{"id":117,"url":"/musicvideo.php?vid=00780d6ba"},{"id":118,"url":"/musicvideo.php?vid=9ba62111f"},{"id":119,"url":"/musicvideo.php?vid=6e64aa258"},{"id":120,"url":"/musicvideo.php?vid=4aa147662"},{"id":121,"url":"/musicvideo.php?vid=56ce730ef"},{"id":122,"url":"/musicvideo.php?vid=de877297d"},{"id":123,"url":"/musicvideo.php?vid=f6ece4e8d"},{"id":124,"url":"/musicvideo.php?vid=3873b19c4"},{"id":125,"url":"/musicvideo.php?vid=12a0f2a1d"},{"id":126,"url":"/musicvideo.php?vid=5c63f7eee"},{"id":127,"url":"/musicvideo.php?vid=9df28046c"},{"id":128,"url":"/musicvideo.php?vid=f0daef3b7"},{"id":129,"url":"/musicvideo.php?vid=cdcee122c"},{"id":130,"url":"/musicvideo.php?vid=05066ce90"},{"id":131,"url":"/musicvideo.php?vid=8863566d1"},{"id":132,"url":"/musicvideo.php?vid=4e8e3ea43"},{"id":133,"url":"/musicvideo.php?vid=d0f2e42f7"},{"id":134,"url":"/musicvideo.php?vid=a33ea9f02"},{"id":135,"url":"/musicvideo.php?vid=3ce72f365"},{"id":136,"url":"/musicvideo.php?vid=1594b1159"},{"id":137,"url":"/musicvideo.php?vid=d570b6b43"},{"id":138,"url":"/musicvideo.php?vid=d3fc0e8d3"},{"id":139,"url":"/musicvideo.php?vid=e3b45c2c2"},{"id":140,"url":"/musicvideo.php?vid=2a06b63d5"},{"id":141,"url":"/musicvideo.php?vid=0a71b7a7b"},{"id":142,"url":"/musicvideo.php?vid=94afbf0d4"},{"id":143,"url":"/musicvideo.php?vid=66391159b"},{"id":144,"url":"/musicvideo.php?vid=cafff04b1"},{"id":145,"url":"/musicvideo.php?vid=4e680bf4c"},{"id":146,"url":"/musicvideo.php?vid=933f5a688"},{"id":147,"url":"/musicvideo.php?vid=67e98d3b9"},{"id":148,"url":"/musicvideo.php?vid=350a3eba7"},{"id":149,"url":"/musicvideo.php?vid=c894affec"},{"id":150,"url":"/musicvideo.php?vid=0450d4b2d"},{"id":151,"url":"/musicvideo.php?vid=2dd6db3d5"},{"id":152,"url":"/musicvideo.php?vid=9f91108a9"},{"id":153,"url":"/musicvideo.php?vid=825ffabc1"},{"id":154,"url":"/musicvideo.php?vid=e31b3e744"},{"id":155,"url":"/musicvideo.php?vid=e0404ad62"},{"id":156,"url":"/musicvideo.php?vid=a37485a8c"},{"id":157,"url":"/musicvideo.php?vid=3debbdb3a"},{"id":158,"url":"/musicvideo.php?vid=2d655f76f"},{"id":159,"url":"/musicvideo.php?vid=7e496ef85"},{"id":160,"url":"/musicvideo.php?vid=df2aa4e2e"},{"id":161,"url":"/musicvideo.php?vid=7ff38bce2"},{"id":162,"url":"/musicvideo.php?vid=66570384d"},{"id":163,"url":"/musicvideo.php?vid=f15f3c90e"},{"id":164,"url":"/musicvideo.php?vid=6ccb4edaa"},{"id":165,"url":"/musicvideo.php?vid=a86fbaae8"},{"id":166,"url":"/musicvideo.php?vid=4ff8f0f37"},{"id":167,"url":"/musicvideo.php?vid=49c7936d1"},{"id":168,"url":"/musicvideo.php?vid=f381daf40"},{"id":169,"url":"/musicvideo.php?vid=be3f8350e"},{"id":170,"url":"/musicvideo.php?vid=c0aed81d9"},{"id":171,"url":"/musicvideo.php?vid=539e32cce"},{"id":172,"url":"/musicvideo.php?vid=6de5e5214"},{"id":173,"url":"/musicvideo.php?vid=087099e2b"},{"id":174,"url":"/musicvideo.php?vid=ec8cc5869"},{"id":175,"url":"/musicvideo.php?vid=4a8049166"},{"id":176,"url":"/musicvideo.php?vid=bc750c70c"},{"id":177,"url":"/musicvideo.php?vid=bad3955c5"},{"id":178,"url":"/musicvideo.php?vid=f83000806"},{"id":179,"url":"/musicvideo.php?vid=f5468d307"},{"id":180,"url":"/musicvideo.php?vid=085ba54b4"},{"id":181,"url":"/musicvideo.php?vid=1583d7ccf"},{"id":182,"url":"/musicvideo.php?vid=54c58f0f1"},{"id":183,"url":"/musicvideo.php?vid=add85173b"},{"id":184,"url":"/musicvideo.php?vid=0283b7e4d"},{"id":185,"url":"/musicvideo.php?vid=ed6bd22b2"},{"id":186,"url":"/musicvideo.php?vid=095442f93"},{"id":187,"url":"/musicvideo.php?vid=b68ec51fc"},{"id":188,"url":"/musicvideo.php?vid=d121eb7a1"},{"id":189,"url":"/musicvideo.php?vid=90554fc0a"},{"id":190,"url":"/musicvideo.php?vid=c5939bd2a"},{"id":191,"url":"/musicvideo.php?vid=d7fc7205c"},{"id":192,"url":"/musicvideo.php?vid=6824e37a0"},{"id":193,"url":"/musicvideo.php?vid=ded7167b0"},{"id":194,"url":"/musicvideo.php?vid=5c173ce5f"},{"id":195,"url":"/musicvideo.php?vid=460429025"},{"id":196,"url":"/musicvideo.php?vid=08e9380c1"},{"id":197,"url":"/musicvideo.php?vid=b59f1c809"},{"id":198,"url":"/musicvideo.php?vid=ccc03cadc"},{"id":199,"url":"/musicvideo.php?vid=16617c1d3"},{"id":200,"url":"/musicvideo.php?vid=e684ad44a"},{"id":201,"url":"/musicvideo.php?vid=dbf687d70"},{"id":202,"url":"/musicvideo.php?vid=f023ec01c"},{"id":203,"url":"/musicvideo.php?vid=f0b400ac0"},{"id":204,"url":"/musicvideo.php?vid=7916017ea"},{"id":205,"url":"/musicvideo.php?vid=8f3f92f40"},{"id":206,"url":"/musicvideo.php?vid=eb7f0f2c2"},{"id":207,"url":"/musicvideo.php?vid=ee973056f"},{"id":208,"url":"/musicvideo.php?vid=6236732d8"},{"id":209,"url":"/musicvideo.php?vid=1fa25e04d"},{"id":210,"url":"/musicvideo.php?vid=8812a115c"},{"id":211,"url":"/musicvideo.php?vid=3a71f5a81"},{"id":212,"url":"/musicvideo.php?vid=3c8bf5724"},{"id":213,"url":"/musicvideo.php?vid=53bd30d80"},{"id":214,"url":"/musicvideo.php?vid=7fe2daeff"},{"id":215,"url":"/musicvideo.php?vid=568096ea6"},{"id":216,"url":"/musicvideo.php?vid=f88b0b110"},{"id":217,"url":"/musicvideo.php?vid=a816ee108"},{"id":218,"url":"/musicvideo.php?vid=b89f84a9d"},{"id":219,"url":"/musicvideo.php?vid=91bff0472"},{"id":220,"url":"/musicvideo.php?vid=a7902ed94"},{"id":221,"url":"/musicvideo.php?vid=c663bd675"},{"id":222,"url":"/musicvideo.php?vid=7a83c1c8f"},{"id":223,"url":"/musicvideo.php?vid=f1d2e19df"},{"id":224,"url":"/musicvideo.php?vid=da0f0c9e2"},{"id":225,"url":"/musicvideo.php?vid=57067ddf6"},{"id":226,"url":"/musicvideo.php?vid=fd1cfd5d8"},{"id":227,"url":"/musicvideo.php?vid=a30f763cf"},{"id":228,"url":"/musicvideo.php?vid=84403e547"},{"id":229,"url":"/musicvideo.php?vid=68d77f810"},{"id":230,"url":"/musicvideo.php?vid=8aafd088f"},{"id":231,"url":"/musicvideo.php?vid=c6fb35eb1"},{"id":232,"url":"/musicvideo.php?vid=9707b22bb"},{"id":233,"url":"/musicvideo.php?vid=f5417ad12"},{"id":234,"url":"/musicvideo.php?vid=7d9200bf9"},{"id":235,"url":"/musicvideo.php?vid=6273aeb39"},{"id":236,"url":"/musicvideo.php?vid=d0b51569c"},{"id":237,"url":"/musicvideo.php?vid=00d7d97dd"},{"id":238,"url":"/musicvideo.php?vid=9c6bebd6a"},{"id":239,"url":"/musicvideo.php?vid=42e6ac4ee"},{"id":240,"url":"/musicvideo.php?vid=da333e048"},{"id":241,"url":"/musicvideo.php?vid=428b0fc29"},{"id":242,"url":"/musicvideo.php?vid=e55ae9eaa"},{"id":243,"url":"/musicvideo.php?vid=a3f7307fe"},{"id":244,"url":"/musicvideo.php?vid=6df67fda9"},{"id":245,"url":"/musicvideo.php?vid=c867c9572"},{"id":246,"url":"/musicvideo.php?vid=2f5461828"},{"id":247,"url":"/musicvideo.php?vid=2ab57101a"},{"id":248,"url":"/musicvideo.php?vid=fe1206446"},{"id":249,"url":"/musicvideo.php?vid=fb8f82ae9"},{"id":250,"url":"/musicvideo.php?vid=c93c8fe84"},{"id":251,"url":"/musicvideo.php?vid=e946ae0e4"},{"id":252,"url":"/musicvideo.php?vid=a5dd7882e"},{"id":253,"url":"/musicvideo.php?vid=89e622445"},{"id":254,"url":"/musicvideo.php?vid=718490f83"},{"id":255,"url":"/musicvideo.php?vid=38ddc88dc"},{"id":256,"url":"/musicvideo.php?vid=24dceffbb"},{"id":257,"url":"/musicvideo.php?vid=02946969d"},{"id":258,"url":"/musicvideo.php?vid=0a8e1b1fd"},{"id":259,"url":"/musicvideo.php?vid=728acc73d"},{"id":260,"url":"/musicvideo.php?vid=b7d489687"},{"id":261,"url":"/musicvideo.php?vid=8d78b865f"},{"id":262,"url":"/musicvideo.php?vid=34cf4d2c2"},{"id":263,"url":"/musicvideo.php?vid=a63a8df9d"},{"id":264,"url":"/musicvideo.php?vid=8b9ad1ff2"},{"id":265,"url":"/musicvideo.php?vid=20c3b4d77"},{"id":266,"url":"/musicvideo.php?vid=4a3bcc05f"},{"id":267,"url":"/musicvideo.php?vid=20c2dada5"},{"id":268,"url":"/musicvideo.php?vid=b4e02f25c"},{"id":269,"url":"/musicvideo.php?vid=40b0271d9"},{"id":270,"url":"/musicvideo.php?vid=b8b19e7ad"},{"id":271,"url":"/musicvideo.php?vid=83cec4121"},{"id":272,"url":"/musicvideo.php?vid=6ee670ad9"},{"id":273,"url":"/musicvideo.php?vid=0e07299b5"},{"id":274,"url":"/musicvideo.php?vid=9a7fa2dca"},{"id":275,"url":"/musicvideo.php?vid=d95192c2f"},{"id":276,"url":"/musicvideo.php?vid=caee66ed4"},{"id":277,"url":"/musicvideo.php?vid=06004e39e"},{"id":278,"url":"/musicvideo.php?vid=57775ae4d"},{"id":279,"url":"/musicvideo.php?vid=69f9f5dcb"},{"id":280,"url":"/musicvideo.php?vid=ff6312b85"},{"id":281,"url":"/musicvideo.php?vid=0e059d749"},{"id":282,"url":"/musicvideo.php?vid=b1e9f091b"},{"id":283,"url":"/musicvideo.php?vid=198fd3a71"},{"id":284,"url":"/musicvideo.php?vid=819221827"},{"id":285,"url":"/musicvideo.php?vid=28d0e32b9"},{"id":286,"url":"/musicvideo.php?vid=c3a358445"},{"id":287,"url":"/musicvideo.php?vid=336f7c23a"},{"id":288,"url":"/musicvideo.php?vid=2074ec269"},{"id":289,"url":"/musicvideo.php?vid=299c7b1e4"},{"id":290,"url":"/musicvideo.php?vid=d23ed58b8"},{"id":291,"url":"/musicvideo.php?vid=3750d0278"},{"id":292,"url":"/musicvideo.php?vid=87623e04b"},{"id":293,"url":"/musicvideo.php?vid=4ea7c81bf"},{"id":294,"url":"/musicvideo.php?vid=6b614f438"},{"id":295,"url":"/musicvideo.php?vid=e642c3bf4"},{"id":296,"url":"/musicvideo.php?vid=cffb432f7"},{"id":297,"url":"/musicvideo.php?vid=ffff40603"},{"id":298,"url":"/musicvideo.php?vid=9fa50310a"},{"id":299,"url":"/musicvideo.php?vid=f4ef04da4"},{"id":300,"url":"/musicvideo.php?vid=17c2afad0"},{"id":301,"url":"/musicvideo.php?vid=35d112a3f"},{"id":302,"url":"/musicvideo.php?vid=69fcbd3c6"},{"id":303,"url":"/musicvideo.php?vid=7d43263b6"},{"id":304,"url":"/musicvideo.php?vid=39035d567"},{"id":305,"url":"/musicvideo.php?vid=cdbd4f2c7"},{"id":306,"url":"/musicvideo.php?vid=a794e7aac"},{"id":307,"url":"/musicvideo.php?vid=cc547010f"},{"id":308,"url":"/musicvideo.php?vid=035eef4b7"},{"id":309,"url":"/musicvideo.php?vid=a3a0c63bf"},{"id":310,"url":"/musicvideo.php?vid=9fdca88b3"},{"id":311,"url":"/musicvideo.php?vid=fe8f38754"},{"id":312,"url":"/musicvideo.php?vid=f1e2029ec"},{"id":313,"url":"/musicvideo.php?vid=0290c17e2"},{"id":314,"url":"/musicvideo.php?vid=9f0e8c72d"},{"id":315,"url":"/musicvideo.php?vid=cfd25a8df"},{"id":316,"url":"/musicvideo.php?vid=e699b5704"},{"id":317,"url":"/musicvideo.php?vid=c4fd2f40a"},{"id":318,"url":"/musicvideo.php?vid=20f44eda1"},{"id":319,"url":"/musicvideo.php?vid=ee08f17ee"},{"id":320,"url":"/musicvideo.php?vid=b4db928fa"},{"id":321,"url":"/musicvideo.php?vid=6283c1647"},{"id":322,"url":"/musicvideo.php?vid=5089b723e"},{"id":323,"url":"/musicvideo.php?vid=a15071c93"},{"id":324,"url":"/musicvideo.php?vid=5b44dfa78"},{"id":325,"url":"/musicvideo.php?vid=eb8bc06fd"},{"id":326,"url":"/musicvideo.php?vid=7ce380f26"},{"id":327,"url":"/musicvideo.php?vid=e77f15e6e"},{"id":328,"url":"/musicvideo.php?vid=802857d5a"},{"id":329,"url":"/musicvideo.php?vid=0fefd53ac"},{"id":330,"url":"/musicvideo.php?vid=7b25f0b33"},{"id":331,"url":"/musicvideo.php?vid=ceb109347"},{"id":332,"url":"/musicvideo.php?vid=b3675b85b"},{"id":333,"url":"/musicvideo.php?vid=8cce52492"},{"id":334,"url":"/musicvideo.php?vid=40ff71af4"},{"id":335,"url":"/musicvideo.php?vid=a89e50478"},{"id":336,"url":"/musicvideo.php?vid=61de159a4"},{"id":337,"url":"/musicvideo.php?vid=0d18eae5d"},{"id":338,"url":"/musicvideo.php?vid=9f19af0da"},{"id":339,"url":"/musicvideo.php?vid=ec0919a1e"},{"id":340,"url":"/musicvideo.php?vid=da12373c3"},{"id":341,"url":"/musicvideo.php?vid=7a2ba54a2"},{"id":342,"url":"/musicvideo.php?vid=55ab6d1a1"},{"id":343,"url":"/musicvideo.php?vid=ba8e19d6b"},{"id":344,"url":"/musicvideo.php?vid=6d1217b40"},{"id":345,"url":"/musicvideo.php?vid=a510077f5"},{"id":346,"url":"/musicvideo.php?vid=9b42a58af"},{"id":347,"url":"/musicvideo.php?vid=7da9f038c"},{"id":348,"url":"/musicvideo.php?vid=193e6acac"},{"id":349,"url":"/musicvideo.php?vid=cb6df498e"},{"id":350,"url":"/musicvideo.php?vid=3608605d3"},{"id":351,"url":"/musicvideo.php?vid=a2c2a2fcf"},{"id":352,"url":"/musicvideo.php?vid=d1c038ac1"},{"id":353,"url":"/musicvideo.php?vid=f91228ed5"},{"id":354,"url":"/musicvideo.php?vid=ecf023cca"},{"id":355,"url":"/musicvideo.php?vid=ddd5d6477"},{"id":356,"url":"/musicvideo.php?vid=e4aab6bfd"},{"id":357,"url":"/musicvideo.php?vid=2908561ab"},{"id":358,"url":"/musicvideo.php?vid=30f90f5fc"},{"id":359,"url":"/musicvideo.php?vid=caaa0a8a6"},{"id":360,"url":"/musicvideo.php?vid=5123b44d4"},{"id":361,"url":"/musicvideo.php?vid=235bcd133"},{"id":362,"url":"/musicvideo.php?vid=12465177f"},{"id":363,"url":"/musicvideo.php?vid=cd56fb973"},{"id":364,"url":"/musicvideo.php?vid=15b3dd7d3"},{"id":365,"url":"/musicvideo.php?vid=d370428e0"},{"id":366,"url":"/musicvideo.php?vid=8b6bab047"},{"id":367,"url":"/musicvideo.php?vid=1dea0fb0b"},{"id":368,"url":"/musicvideo.php?vid=4701f09d4"},{"id":369,"url":"/musicvideo.php?vid=ea27cacad"},{"id":370,"url":"/musicvideo.php?vid=dc576a1fe"},{"id":371,"url":"/musicvideo.php?vid=271f4ca46"},{"id":372,"url":"/musicvideo.php?vid=cf5519155"},{"id":373,"url":"/musicvideo.php?vid=204a26057"},{"id":374,"url":"/musicvideo.php?vid=e4b52060b"},{"id":375,"url":"/musicvideo.php?vid=8dd7cdcc8"},{"id":376,"url":"/musicvideo.php?vid=6061d09f5"},{"id":377,"url":"/musicvideo.php?vid=33a02dd27"},{"id":378,"url":"/musicvideo.php?vid=2bc920936"},{"id":379,"url":"/musicvideo.php?vid=fe588d96e"},{"id":380,"url":"/musicvideo.php?vid=d9fdae784"},{"id":381,"url":"/musicvideo.php?vid=11aac5cf1"},{"id":382,"url":"/musicvideo.php?vid=ed0f9063a"},{"id":383,"url":"/musicvideo.php?vid=7563933b6"},{"id":384,"url":"/musicvideo.php?vid=636164fef"},{"id":385,"url":"/musicvideo.php?vid=4415571b0"},{"id":386,"url":"/musicvideo.php?vid=971f2fbab"},{"id":387,"url":"/musicvideo.php?vid=a1d0b467b"},{"id":388,"url":"/musicvideo.php?vid=a71f59ce7"},{"id":389,"url":"/musicvideo.php?vid=963b9121f"},{"id":390,"url":"/musicvideo.php?vid=38e7be4de"},{"id":391,"url":"/musicvideo.php?vid=a420ea4e2"},{"id":392,"url":"/musicvideo.php?vid=5bfd08127"},{"id":393,"url":"/musicvideo.php?vid=c523859f7"},{"id":394,"url":"/musicvideo.php?vid=c851b59fa"},{"id":395,"url":"/musicvideo.php?vid=6f9379f30"},{"id":396,"url":"/musicvideo.php?vid=d4371b7f4"},{"id":397,"url":"/musicvideo.php?vid=2b439ca3c"},{"id":398,"url":"/musicvideo.php?vid=93d14a8a1"},{"id":399,"url":"/musicvideo.php?vid=b5c811405"},{"id":400,"url":"/musicvideo.php?vid=98fca5241"},{"id":401,"url":"/musicvideo.php?vid=42a647393"},{"id":402,"url":"/musicvideo.php?vid=17055d406"},{"id":403,"url":"/musicvideo.php?vid=f51ad8dbb"},{"id":404,"url":"/musicvideo.php?vid=4ff4fd54b"},{"id":405,"url":"/musicvideo.php?vid=13ecbb450"},{"id":406,"url":"/musicvideo.php?vid=55f19a256"},{"id":407,"url":"/musicvideo.php?vid=2bc02e10c"},{"id":408,"url":"/musicvideo.php?vid=3b94f1a5f"},{"id":409,"url":"/musicvideo.php?vid=8b4009d36"},{"id":410,"url":"/musicvideo.php?vid=03207ccc6"},{"id":411,"url":"/musicvideo.php?vid=e8d686358"},{"id":412,"url":"/musicvideo.php?vid=69f57d8c5"},{"id":413,"url":"/musicvideo.php?vid=98a16f8f8"},{"id":414,"url":"/musicvideo.php?vid=fbbaa045d"},{"id":415,"url":"/musicvideo.php?vid=9fe487de5"},{"id":416,"url":"/musicvideo.php?vid=b95d71f59"},{"id":417,"url":"/musicvideo.php?vid=cbb8ddb4f"},{"id":418,"url":"/musicvideo.php?vid=a497e7b5c"},{"id":419,"url":"/musicvideo.php?vid=5f557a01b"},{"id":420,"url":"/musicvideo.php?vid=8213dee67"},{"id":421,"url":"/musicvideo.php?vid=51fc644e6"},{"id":422,"url":"/musicvideo.php?vid=2472dbd54"},{"id":423,"url":"/musicvideo.php?vid=427301540"},{"id":424,"url":"/musicvideo.php?vid=5bcf39297"},{"id":425,"url":"/musicvideo.php?vid=5d6649e57"},{"id":426,"url":"/musicvideo.php?vid=dae596820"},{"id":427,"url":"/musicvideo.php?vid=d169e9829"},{"id":428,"url":"/musicvideo.php?vid=11048754b"},{"id":429,"url":"/musicvideo.php?vid=c445bdcaa"},{"id":430,"url":"/musicvideo.php?vid=e20cc01c8"},{"id":431,"url":"/musicvideo.php?vid=3afe64d19"},{"id":432,"url":"/musicvideo.php?vid=3826a9fbb"},{"id":433,"url":"/musicvideo.php?vid=e80369190"},{"id":434,"url":"/musicvideo.php?vid=826f880d3"},{"id":435,"url":"/musicvideo.php?vid=79d98f71f"},{"id":436,"url":"/musicvideo.php?vid=bf6b250d8"},{"id":437,"url":"/musicvideo.php?vid=345598433"},{"id":438,"url":"/musicvideo.php?vid=8d233d5c2"},{"id":439,"url":"/musicvideo.php?vid=d700e7569"},{"id":440,"url":"/musicvideo.php?vid=de6644533"},{"id":441,"url":"/musicvideo.php?vid=c5d410b62"},{"id":442,"url":"/musicvideo.php?vid=ea6ab4cf4"},{"id":443,"url":"/musicvideo.php?vid=2343d4076"},{"id":444,"url":"/musicvideo.php?vid=0bb2d388f"},{"id":445,"url":"/musicvideo.php?vid=c32b92f23"},{"id":446,"url":"/musicvideo.php?vid=d4bfa73b3"},{"id":447,"url":"/musicvideo.php?vid=85ad2b444"},{"id":448,"url":"/musicvideo.php?vid=43cb077cc"},{"id":449,"url":"/musicvideo.php?vid=c3ba736d5"},{"id":450,"url":"/musicvideo.php?vid=47912e57e"},{"id":451,"url":"/musicvideo.php?vid=d9ef0aefe"},{"id":452,"url":"/musicvideo.php?vid=fef5232ad"},{"id":453,"url":"/musicvideo.php?vid=c0991b7aa"},{"id":454,"url":"/musicvideo.php?vid=21740e564"},{"id":455,"url":"/musicvideo.php?vid=c78b2909f"},{"id":456,"url":"/musicvideo.php?vid=e710491ab"},{"id":457,"url":"/musicvideo.php?vid=70f69fb4f"},{"id":458,"url":"/musicvideo.php?vid=c458278da"},{"id":459,"url":"/musicvideo.php?vid=562b159e4"},{"id":460,"url":"/musicvideo.php?vid=aff3026b1"},{"id":461,"url":"/musicvideo.php?vid=914ccd610"},{"id":462,"url":"/musicvideo.php?vid=94ea961a5"},{"id":463,"url":"/musicvideo.php?vid=119122092"},{"id":464,"url":"/musicvideo.php?vid=7356ac122"},{"id":465,"url":"/musicvideo.php?vid=97ad1be18"},{"id":466,"url":"/musicvideo.php?vid=86a9a840f"},{"id":467,"url":"/musicvideo.php?vid=1206a3d6c"},{"id":468,"url":"/musicvideo.php?vid=09668641a"},{"id":469,"url":"/musicvideo.php?vid=19a2dcb01"},{"id":470,"url":"/musicvideo.php?vid=d57190274"},{"id":471,"url":"/musicvideo.php?vid=44e822a38"},{"id":472,"url":"/musicvideo.php?vid=f551fb8cc"},{"id":473,"url":"/musicvideo.php?vid=4e8f6b80d"},{"id":474,"url":"/musicvideo.php?vid=fb4960a09"},{"id":475,"url":"/musicvideo.php?vid=204384c80"},{"id":476,"url":"/musicvideo.php?vid=c3d4c4b82"},{"id":477,"url":"/musicvideo.php?vid=928dab67f"},{"id":478,"url":"/musicvideo.php?vid=c5a163437"},{"id":479,"url":"/musicvideo.php?vid=3bd2f3717"},{"id":480,"url":"/musicvideo.php?vid=49203b7c1"},{"id":481,"url":"/musicvideo.php?vid=0a939e9b0"},{"id":482,"url":"/musicvideo.php?vid=2b602ae85"},{"id":483,"url":"/musicvideo.php?vid=b436ef0e3"},{"id":484,"url":"/musicvideo.php?vid=95eefa1f0"},{"id":485,"url":"/musicvideo.php?vid=948da9393"},{"id":486,"url":"/musicvideo.php?vid=fe65cc122"},{"id":487,"url":"/musicvideo.php?vid=cf5868d41"},{"id":488,"url":"/musicvideo.php?vid=e786e0381"},{"id":489,"url":"/musicvideo.php?vid=9be8dda50"},{"id":490,"url":"/musicvideo.php?vid=fae65fa75"},{"id":491,"url":"/musicvideo.php?vid=af21fe8b9"},{"id":492,"url":"/musicvideo.php?vid=42d8dbd3c"},{"id":493,"url":"/musicvideo.php?vid=d299f5609"},{"id":494,"url":"/musicvideo.php?vid=50a241176"},{"id":495,"url":"/musicvideo.php?vid=cec113476"},{"id":496,"url":"/musicvideo.php?vid=710ae60aa"},{"id":497,"url":"/musicvideo.php?vid=42f109b13"},{"id":498,"url":"/musicvideo.php?vid=4c2d01c96"},{"id":499,"url":"/musicvideo.php?vid=7a52c1194"},{"id":500,"url":"/musicvideo.php?vid=95d72e129"},{"id":501,"url":"/musicvideo.php?vid=64b6dddde"},{"id":502,"url":"/musicvideo.php?vid=a2aa912ab"},{"id":503,"url":"/musicvideo.php?vid=59215bef8"},{"id":504,"url":"/musicvideo.php?vid=6c9b7f8ba"},{"id":505,"url":"/musicvideo.php?vid=151e2f9b5"},{"id":506,"url":"/musicvideo.php?vid=490f80b77"},{"id":507,"url":"/musicvideo.php?vid=e4409b6c0"},{"id":508,"url":"/musicvideo.php?vid=2b4048f16"},{"id":509,"url":"/musicvideo.php?vid=be686b287"},{"id":510,"url":"/musicvideo.php?vid=2f155f780"},{"id":511,"url":"/musicvideo.php?vid=20453f51c"},{"id":512,"url":"/musicvideo.php?vid=af8dc5287"},{"id":513,"url":"/musicvideo.php?vid=06f454c95"},{"id":514,"url":"/musicvideo.php?vid=ce0654e66"},{"id":515,"url":"/musicvideo.php?vid=29c4f77fc"},{"id":516,"url":"/musicvideo.php?vid=3f7cbfd5c"},{"id":517,"url":"/musicvideo.php?vid=42a16dd9d"},{"id":518,"url":"/musicvideo.php?vid=214129660"},{"id":519,"url":"/musicvideo.php?vid=9b51f9db8"},{"id":520,"url":"/musicvideo.php?vid=cdf443b88"},{"id":521,"url":"/musicvideo.php?vid=bc3a09f04"},{"id":522,"url":"/musicvideo.php?vid=ef97ecdbd"},{"id":523,"url":"/musicvideo.php?vid=05f81c1f7"},{"id":524,"url":"/musicvideo.php?vid=fdd956be9"},{"id":525,"url":"/musicvideo.php?vid=030b35f7a"},{"id":526,"url":"/musicvideo.php?vid=997098efb"},{"id":527,"url":"/musicvideo.php?vid=6c4e609ab"},{"id":528,"url":"/musicvideo.php?vid=36bce3c17"},{"id":529,"url":"/musicvideo.php?vid=3e9499374"},{"id":530,"url":"/musicvideo.php?vid=55ac16357"},{"id":531,"url":"/musicvideo.php?vid=49cd25e4c"},{"id":532,"url":"/musicvideo.php?vid=a8f25f23a"},{"id":533,"url":"/musicvideo.php?vid=195de69d8"},{"id":534,"url":"/musicvideo.php?vid=3a0c67e0e"},{"id":535,"url":"/musicvideo.php?vid=f9dc76ee2"},{"id":536,"url":"/musicvideo.php?vid=bc1ce6c60"},{"id":537,"url":"/musicvideo.php?vid=3e0f0ccdf"},{"id":538,"url":"/musicvideo.php?vid=09e4a2ba3"},{"id":539,"url":"/musicvideo.php?vid=733808cc6"},{"id":540,"url":"/musicvideo.php?vid=d70c9cbe1"},{"id":541,"url":"/musicvideo.php?vid=80b2c8423"},{"id":542,"url":"/musicvideo.php?vid=2b43a1587"},{"id":543,"url":"/musicvideo.php?vid=72cf30cd4"},{"id":544,"url":"/musicvideo.php?vid=d0e900eb1"},{"id":545,"url":"/musicvideo.php?vid=72c458a59"},{"id":546,"url":"/musicvideo.php?vid=64600d53b"},{"id":547,"url":"/musicvideo.php?vid=2635b0510"},{"id":548,"url":"/musicvideo.php?vid=106298c6f"},{"id":549,"url":"/musicvideo.php?vid=d8010a769"},{"id":550,"url":"/musicvideo.php?vid=3be8785f3"},{"id":551,"url":"/musicvideo.php?vid=8826ff774"},{"id":552,"url":"/musicvideo.php?vid=60863df7f"},{"id":553,"url":"/musicvideo.php?vid=d06c9ef6b"},{"id":554,"url":"/musicvideo.php?vid=b97ac68f9"},{"id":555,"url":"/musicvideo.php?vid=78fc21bf3"},{"id":556,"url":"/os-simpsons-24%c2%aa-temporada-episodio-01-um-rio-de-emocoes-video_7e33e4be4.html"},{"id":557,"url":"/os-simpsons-24%c2%aa-temporada-episodio-02-a-casa-da-arvore-dos-horrores-xxiii-video_f98d1a31a.html"},{"id":558,"url":"/os-simpsons-24%c2%aa-temporada-episodio-03-bebe-a-bordo-video_0b011b5d3.html"},{"id":559,"url":"/os-simpsons-24%C2%AA-temporada-episodio-04-o-sumico-de-abie-video_0e9f8807f.html"},{"id":560,"url":"/os-simpsons-24%c2%aa-temporada-episodio-05-acertando-as-contas-video_a3a40f909.html"},{"id":561,"url":"/os-simpsons-24a-temporada-episodio-06-cresce-uma-arvore-em-springfield-video_2fe5fddd5.html"},{"id":562,"url":"/os-simpsons-24a-temporada-episodio-07-o-dia-em-que-a-terra-ficou-bacana-video_c49d7e9d1.html"},{"id":563,"url":"/os-simpsons-24a-temporada-episodio-08-para-um-vira-lata-com-amor-video_382d3470b.html"},{"id":564,"url":"/os-simpsons-24a-temporada-episodio-09-homer-preparado-para-o-fim-video_ec58f0199.html"},{"id":565,"url":"/os-simpsons-24a-temporada-episodio-10-um-teste-antes-de-tentar-video_895d79a58.html"},{"id":566,"url":"/os-simpsons-24a-temporada-episodio-11-em-busca-dos-tutores-video_42176f10c.html"},{"id":567,"url":"/os-simpsons-24a-temporada-episodio-12-amar-e-de-lascar-video_b96b8bd5f.html"},{"id":568,"url":"/os-simpsons-24a-temporada-episodio-13-eu-sou-voce-amanha-video_a9a81bcc5.html"},{"id":569,"url":"/os-simpsons-24a-temporada-episodio-14-vaidoso-vovo-video_8d7ca6ae0.html"},{"id":570,"url":"/os-simpsons-24a-temporada-episodio-15-olho-por-olho-video_5fd52c02a.html"},{"id":571,"url":"/os-simpsons-24a-temporada-episodio-16-o-morcego-justiceiro-e-a-corte-juvenil-video_48aa27002.html"},{"id":572,"url":"/os-simpsons-24a-temporada-episodio-17-do-que-as-mulheres-gostam-video_a7e7cf5c3.html"},{"id":573,"url":"/os-simpsons-24a-temporada-episodio-18-tempo-de-violencia-video_0ed32ec35.html"},{"id":574,"url":"/os-simpsons-24a-temporada-episodio-19-negocio-muito-ariscado-video_98a12e9c6.html"},{"id":575,"url":"/os-simpsons-24a-temporada-episodio-20-o-pequeno-impostor-video_0c6f302ca.html"},{"id":576,"url":"/os-simpsons-24a-temporada-episodio-21-a-saga-de-carl-video_3a86f7c4c.html"},{"id":577,"url":"/os-simpsons-24a-temporada-episodio-22-perigos-em-um-trem-video_437f0a4ac.html"},{"id":578,"url":"/os-simpsons-25a-temporada-episodio-01-homerland_fdf36a0a7.html"},{"id":579,"url":"/os-simpsons-25a-temporada-episodio-02-a-casa-da-arvore-dos-horrores-xxiv_913858a20.html"},{"id":580,"url":"/os-simpsons-25a-temporada-episodio-03-quatro-arrependimentos-e-um-funeral_16a35f5ee.html"},{"id":581,"url":"/os-simpsons-25a-temporada-episodio-04-so-se-vive-uma-vez_280f70d36.html"},{"id":582,"url":"/os-simpsons-25a-temporada-episodio-05-um-parto-inesquecivel_e0e819b4e.html"},{"id":583,"url":"/os-simpsons-25a-temporada-episodio-06-uma-amiga-para-lisa_636459cbc.html"},{"id":584,"url":"/os-simpsons-25a-temporada-episodio-07-um-submarino-que-nao-era-amarelo_5925155b5.html"},{"id":585,"url":"/os-simpsons-25a-temporada-episodio-08-um-natal-pra-la-de-especial_5fafbbc67.html"},{"id":586,"url":"/os-simpsons-25a-temporada-episodio-09-o-pirata-prateado_5bab81753.html"},{"id":587,"url":"/os-simpsons-25a-temporada-episodio-10-casada-com-o-blob_ccd56d268.html"},{"id":588,"url":"/os-simpsons-25a-temporada-episodio-11-a-vida-secreta-de-marge_3811d5de5.html"},{"id":589,"url":"/os-simpsons-25a-temporada-episodio-12-nas-asas-da-loucura_d6da8f142.html"},{"id":590,"url":"/os-simpsons-25a-temporada-episodio-13-o-homem-que-evoluiu-demais_6bff48edf.html"},{"id":591,"url":"/os-simpsons-25a-temporada-episodio-14-tres-anciaos-e-um-pupilo_5320033d5.html"},{"id":592,"url":"/os-simpsons-25a-temporada-episodio-15-a-guerra-da-arte_189b3636f.html"},{"id":593,"url":"/os-simpsons-25a-temporada-episodio-16-os-simpsons-na-copa-do-mundo_710031aaf.html"},{"id":594,"url":"/os-simpsons-25a-temporada-episodio-17-pais-e-filhos_937f64227.html"},{"id":595,"url":"/os-simpsons-25a-temporada-episodio-18-dias-de-um-futuro-futuro_4040c0141.html"},{"id":596,"url":"/os-simpsons-25a-temporada-episodio-19-o-que-esperar-quando-bart-esta-esperando_2cae987ca.html"},{"id":597,"url":"/os-simpsons-25a-temporada-episodio-20-blocos-vorazes_40d9b86db.html"},{"id":598,"url":"/os-simpsons-25a-temporada-episodio-21-amigos-comprados_7527bb09b.html"},{"id":599,"url":"/os-simpsons-25a-temporada-episodio-22-a-ligeira-gloria-de-um-covarde_96d5cbe97.html"},{"id":600,"url":"/os-simpsons-26a-temporada-episodio-01-lagrimas-de-um-palhaco_ba210f552.html"},{"id":601,"url":"/os-simpsons-26a-temporada-episodio-02-quando-o-relacionamento-afunda_8bbb328dd.html"},{"id":602,"url":"/os-simpsons-26a-temporada-episodio-03-negocio-de-familia_321a1be43.html"},{"id":603,"url":"/os-simpsons-26a-temporada-episodio-04-a-casa-da-arvore-de-horror-xxv_7bb159d2a.html"},{"id":604,"url":"/os-simpsons-26a-temporada-episodio-05-simpsorama_22a116871.html"},{"id":605,"url":"/os-simpsons-26a-temporada-episodio-06-simpsorama_1d8e0b806.html"},{"id":606,"url":"/os-simpsons-26a-temporada-episodio-07-quem-ri-por-ultimo_42266ffe4.html"},{"id":607,"url":"/os-simpsons-26a-temporada-episodio-08-a-banda-covercraft_838be6391.html"},{"id":608,"url":"/os-simpsons-26a-temporada-episodio-09-um-natal-sem-fami%cc%81lia_f1330f486.html"},{"id":609,"url":"/os-simpsons-26a-temporada-episodio-10-um-banquete-indigesto_4cf787f41.html"},{"id":610,"url":"/os-simpsons-26a-temporada-episodio-11-o-novo-amigo-do-bart_9f0f9a0fa.html"},{"id":611,"url":"/os-simpsons-26a-temporada-episodio-12-o-homem-que-caiu-do-ceu_fc6f27e1e.html"},{"id":612,"url":"/os-simpsons-26a-temporada-episodio-13-revolta-de-peso_5566f24d0.html"},{"id":613,"url":"/os-simpsons-26a-temporada-episodio-14-quer-uma-carona_3aebc0fcc.html"},{"id":614,"url":"/os-simpsons-26a-temporada-episodio-15-uma-princesa-em-springfield_6be57627b.html"},{"id":615,"url":"/os-simpsons-26a-temporada-episodio-16-patrulha-do-ceu_d6002aa53.html"},{"id":616,"url":"/os-simpsons-26a-temporada-episodio-17-esperando-o-sr-duffman_fd146f317.html"},{"id":617,"url":"/os-simpsons-26a-temporada-episodio-18-de-olhos-bem-abertos_7fc5ee30d.html"},{"id":618,"url":"/os-simpsons-26a-temporada-episodio-19-em-pe-de-guerra_833efd57e.html"},{"id":619,"url":"/os-simpsons-26a-temporada-episodio-20-licoes-do-passado_38f8d3481.html"},{"id":620,"url":"/os-simpsons-26a-temporada-episodio-21-chega-de-bullying_6ec49a0d8.html"},{"id":621,"url":"/os-simpsons-26a-temporada-episodio-22-atletas-da-matematica_3fd4e5519.html"},{"id":622,"url":"/os-simpsons-27a-temporada-episodio-01-o-sonho-de-todo-homem_275deb4b4.html"},{"id":623,"url":"/os-simpsons-27a-temporada-episodio-02-bancando-os-detetives_f32d49262.html"},{"id":624,"url":"/os-simpsons-27a-temporada-episodio-03-adeus-fumaca_5033d3a50.html"},{"id":625,"url":"/os-simpsons-27a-temporada-episodio-04-terror-de-halloween_1790206be.html"},{"id":626,"url":"/os-simpsons-27a-temporada-episodio-05-a-casa-da-arvore-de-horror-xxvi_0425878b0.html"},{"id":627,"url":"/os-simpsons-27a-temporada-episodio-06-uma-amizade-interessante_5cf54116e.html"},{"id":628,"url":"/os-simpsons-27a-temporada-episodio-07-lisa-com-s_4e0665cd7.html"},{"id":629,"url":"/os-simpsons-27a-temporada-episodio-08-caminhos-de-gloria_54c3fec6c.html"},{"id":630,"url":"/os-simpsons-27a-temporada-episodio-09-barthood_3ef49f564.html"},{"id":631,"url":"/os-simpsons-27a-temporada-episodio-10-programas-de-meninas_390e42200.html"},{"id":632,"url":"/os-simpsons-27a-temporada-episodio-11-o-leite-modificado-e-a-ameaca-mutante_4ece94e14.html"},{"id":633,"url":"/os-simpsons-27a-temporada-episodio-12-ruina-e-redencao-de-abu_e7abaf549.html"},{"id":634,"url":"/os-simpsons-27a-temporada-episodio-13-a-quimica-do-amor_9ecf7045b.html"},{"id":635,"url":"/os-simpsons-27a-temporada-episodio-14-uma-vida-sofrida_08047ad8a.html"},{"id":636,"url":"/os-simpsons-27a-temporada-episodio-15-lisa-a-veterinaria_0c5f49bbb.html"},{"id":637,"url":"/os-simpsons-27a-temporada-episodio-16-marge-em-marte_b99fdc5c6.html"},{"id":638,"url":"/os-simpsons-27a-temporada-episodio-17-prisioneiro-do-amor_6031587ae.html"},{"id":639,"url":"/os-simpsons-27a-temporada-episodio-18-reconquistando-lisa_a7dee2e80.html"},{"id":640,"url":"/os-simpsons-27a-temporada-episodio-19-uma-viajem-para-ficar-na-memoria_2751afdc6.html"},{"id":641,"url":"/os-simpsons-27a-temporada-episodio-20-uma-entrega-com-amor_aa4f0c2f3.html"},{"id":642,"url":"/os-simpsons-27a-temporada-episodio-21-improviso_cbacd5fd8.html"},{"id":643,"url":"/os-simpsons-27a-temporada-episodio-22-laranja-e-o-novo-amarelo_708ca6c3b.html"},{"id":644,"url":"/os-simpsons-28a-temporada-episodio-01-o-circo-de-lembrancas-de-monty-burns_aba0a1395.html"},{"id":645,"url":"/os-simpsons-28a-temporada-episodio-02-amigos-e-familia_9084f1d9e.html"},{"id":646,"url":"/os-simpsons-28a-temporada-episodio-03-a-nova-cidade_06643d81c.html"},{"id":647,"url":"/os-simpsons-28a-temporada-episodio-04-a-casa-da-arvore-de-horror-xxvii_96feafa02.html"},{"id":648,"url":"/os-simpsons-28a-temporada-episodio-05-acredite-mas-esclareca_767d43f65.html"},{"id":649,"url":"/os-simpsons-28a-temporada-episodio-06-os-novos-amigos_34af9b7f4.html"},{"id":650,"url":"/os-simpsons-28a-temporada-episodio-07-o-inesquecivel-fim-de-semana-em-havana_9ed8fee14.html"},{"id":651,"url":"/os-simpsons-28a-temporada-episodio-08-pais-e-filhos_f082e28cf.html"},{"id":652,"url":"/os-simpsons-28a-temporada-episodio-09-um-ato-heroico_6ee391d42.html"},{"id":653,"url":"/os-simpsons-28a-temporada-episodio-10-o-natal-especial-do-krusty_7ac805770.html"},{"id":654,"url":"/os-simpsons-28a-temporada-episodio-11-o-velho-e-o-porquinho_af71a1bc2.html"},{"id":655,"url":"/os-simpsons-28a-temporada-episodio-12-o-grande-phatsby-parte-1_1eb0db75a.html"},{"id":656,"url":"/os-simpsons-28a-temporada-episodio-13-o-grande-phatsby-parte-2_bce39b449.html"},{"id":657,"url":"/os-simpsons-28a-temporada-episodio-14-memorias-de-infancia_c4496b545.html"},{"id":658,"url":"/os-simpsons-28a-temporada-episodio-15-um-irmao-de-tirar-o-chapeu_672af0782.html"},{"id":659,"url":"/os-simpsons-28a-temporada-episodio-16-de-volta-ao-acampamento-do-krustier_439b64bcd.html"},{"id":660,"url":"/os-simpsons-28a-temporada-episodio-18-o-relogio-do-papai_f8fc41e3d.html"},{"id":661,"url":"/os-simpsons-28a-temporada-episodio-19-um-formidavel-professor_808e33531.html"},{"id":662,"url":"/os-simpsons-28a-temporada-episodio-20-o-lado-bom-do-bart_312f707f8.html"},{"id":663,"url":"/os-simpsons-28a-temporada-episodio-21-a-aposta_bb969320c.html"},{"id":664,"url":"/os-simpsons-28a-temporada-episodio-22-a-cidade-dos-caes_e0ba02ce2.html"},{"id":665,"url":"/os-simpsons-29a-temporada-episodio-01-os-serfsons_b0eed3e2b.html"},{"id":666,"url":"/os-simpsons-29a-temporada-episodio-02-o-esplendor-de-springfield_a563f6220.html"},{"id":667,"url":"/os-simpsons-29a-temporada-episodio-03-o-pai-de-whistler_9e5326b7e.html"},{"id":668,"url":"/os-simpsons-29a-temporada-episodio-04-a-casa-da-arvore-de-horror-xxviii_d2b33e316.html"},{"id":669,"url":"/os-simpsons-29a-temporada-episodio-05-vovo-esta-me-ouvindo_70d5ff809.html"},{"id":670,"url":"/os-simpsons-29a-temporada-episodio-06-a-velha-prefeita-nao-e-mais-o-que-era_4984a03c3.html"},{"id":671,"url":"/os-simpsons-29a-temporada-episodio-07-cantando-na-pista_80bd610eb.html"},{"id":672,"url":"/os-simpsons-29a-temporada-episodio-08-a-vida-de-lisa_a5a702347.html"},{"id":673,"url":"/os-simpsons-29a-temporada-episodio-09-onde-esta-o-bart_11b813008.html"},{"id":674,"url":"/os-simpsons-29a-temporada-episodio-10-haw-haw-land_c2c750bdd.html"},{"id":675,"url":"/os-simpsons-29a-temporada-episodio-11-o-teste-de-frink_149388e9c.html"},{"id":676,"url":"/os-simpsons-29a-temporada-episodio-12-homer-esta-onde-a-arte-nao-esta_fcf31b501.html"},{"id":677,"url":"/os-simpsons-29a-temporada-episodio-13-3-cenas-e-uma-ponta-de-casamento_9195fe09e.html"},{"id":678,"url":"/os-simpsons-29a-temporada-episodio-14-medos-de-um-palhaco_cee15e203.html"},{"id":679,"url":"/os-simpsons-29a-temporada-episodio-15-aqui-se-ler-aqui-se-paga_9211f4bdb.html"},{"id":680,"url":"/os-simpsons-29a-temporada-episodio-16-traicao-do-rei_91f9f38cd.html"},{"id":681,"url":"/os-simpsons-29a-temporada-episodio-17-a-tristeza-de-lisa_c5edafcf1.html"},{"id":682,"url":"/os-simpsons-29a-temporada-episodio-18-perdoar-e-se-arrepender_4d5b77d8b.html"},{"id":683,"url":"/os-simpsons-29a-temporada-episodio-19-deixado-para-tras_d37a2ef83.html"},{"id":684,"url":"/os-simpsons-29a-temporada-episodio-20-ha-algo-de-podre-no-reino-da-dinamarca_048951062.html"},{"id":685,"url":"/os-simpsons-29a-temporada-episodio-21-a-escada-de-flanders_bf5ff07e6.html"},{"id":686,"url":"/os-simpsons-30a-temporada-episodio-01-bart-nao-esta-morto_6f3e5b187.html"},{"id":687,"url":"/os-simpsons-30a-temporada-episodio-02-hotel-de-desgostos_6de5e1de7.html"},{"id":688,"url":"/os-simpsons-30a-temporada-episodio-03-meu-jeito-ou-a-estrada-para-o-ceu_9a9039821.html"},{"id":689,"url":"/os-simpsons-30a-temporada-episodio-04-a-casa-da-arvore-de-horror-xxix_48d1c5604.html"},{"id":690,"url":"/os-simpsons-30a-temporada-episodio-05-voce-nao-pode-dirigir-meu-carro_18c98e728.html"},{"id":691,"url":"/os-simpsons-30a-temporada-episodio-06-moscou-contra-moe_9d61b5c81.html"},{"id":692,"url":"/os-simpsons-30a-temporada-episodio-07-um-show-de-mulher_792e25f9d.html"},{"id":693,"url":"/os-simpsons-30a-temporada-episodio-08-krusty-o-palhaco_28aeaef96.html"},{"id":694,"url":"/os-simpsons-30a-temporada-episodio-09-daddicus-finch_ddcd6868b.html"},{"id":695,"url":"/os-simpsons-30a-temporada-episodio-10-e-a-30a-temporada_cc5124a22.html"},{"id":696,"url":"/os-simpsons-30a-temporada-episodio-11-louco-por-um-brinquedo_36707ec00.html"},{"id":697,"url":"/os-simpsons-30a-temporada-episodio-12-a-garota-no-onibus_92f99c300.html"},{"id":698,"url":"/os-simpsons-30a-temporada-episodio-13-gordancando-como-louco_a44c8000e.html"},{"id":699,"url":"/os-simpsons-30a-temporada-episodio-14-o-show-do-palhaco-nao-pode-parar_d78df9490.html"},{"id":700,"url":"/os-simpsons-30a-temporada-episodio-15-as-101-mitigacoes_6dee6e45e.html"},{"id":701,"url":"/os-simpsons-30a-temporada-episodio-16-eu-te-quero-tanto-ela-e-tao-pesada_2d3c5d217.html"},{"id":702,"url":"/os-simpsons-30a-temporada-episodio-17-e-my-sports_aa79c6061.html"},{"id":703,"url":"/os-simpsons-30a-temporada-episodio-18-bart-vscomichao-e-cocadinha_d92ed67ee.html"},{"id":704,"url":"/os-simpsons-30a-temporada-episodio-19-a-menina-da-banda_d3b98276c.html"},{"id":705,"url":"/os-simpsons-30a-temporada-episodio-20-apenas-uma-garota-que-nao-sabe-dizer-doh_7e796bd33.html"},{"id":706,"url":"/os-simpsons-30a-temporada-episodio-21-doh-canada_3c771aa5e.html"},{"id":707,"url":"/os-simpsons-30a-temporada-episodio-22-quem-foi_1be8d8c50.html"},{"id":708,"url":"/os-simpsons-30a-temporada-episodio-23-persuasao-do-cabelo-azul-cristal_4a010e0f2.html"},{"id":709,"url":"/os-simpsons-31a-temporada-episodio-01-o-inverno-da-nossa-esperanca-monetizada_8cbf30e42.html"},{"id":710,"url":"/os-simpsons-31a-temporada-episodio-02-vai-com-tudo-ou-vai-com-homer_185c445db.html"},{"id":711,"url":"/os-simpsons-31a-temporada-episodio-03-ladrao-que-rouba-ladrao_efd8a24e3.html"},{"id":712,"url":"/os-simpsons-31a-temporada-episodio-04-a-casa-da-arvore-de-horror-xxx_09c24f27a.html"},{"id":713,"url":"/os-simpsons-31a-temporada-episodio-05-gorila-a-solta_eb3613e15.html"},{"id":714,"url":"/os-simpsons-31a-temporada-episodio-06-marge-a-lenhadora_47b045636.html"},{"id":715,"url":"/os-simpsons-31a-temporada-episodio-07-vivendo-a-pura-vida_4d12c724e.html"},{"id":716,"url":"/os-simpsons-31a-temporada-episodio-08-acao-de-gracas-de-terror_1d783a76d.html"},{"id":717,"url":"/os-simpsons-31a-temporada-episodio-09-todd-todd-por-que-me-abandonaste_b8cf5b6b5.html"},{"id":718,"url":"/os-simpsons-31a-temporada-episodio-10-bobby-faz-frio-la-fora_65beca1ba.html"},{"id":719,"url":"/os-simpsons-31a-temporada-episodio-11-salve-aos-dentes_10e489e97.html"},{"id":720,"url":"/os-simpsons-31a-temporada-episodio-12-a-deseducacao-de-lisa-simpson_fcf20b33c.html"},{"id":721,"url":"/os-simpsons-31a-temporada-episodio-13-frinkcoin_81fd92a06.html"},{"id":722,"url":"/os-simpsons-31a-temporada-episodio-14-bart-o-vilao_2f96288bd.html"},{"id":723,"url":"/os-simpsons-31a-temporada-episodio-15-desconectados_d4b559805.html"},{"id":724,"url":"/os-simpsons-31a-temporada-episodio-16-melhor-com-o-ned_3793833c4.html"},{"id":725,"url":"/os-simpsons-31a-temporada-episodio-17-estrada-ao-inferno_242254c0a.html"},{"id":726,"url":"/os-simpsons-31a-temporada-episodio-18-a-incrivel-leveza-de-ser-um-bebe_af169ee0e.html"},{"id":727,"url":"/os-simpsons-31a-temporada-episodio-19-padres-guerreiros-parte-1_9d4e9fa72.html"},{"id":728,"url":"/os-simpsons-31a-temporada-episodio-20-padres-guerreiros-parte-2_16225e403.html"},{"id":729,"url":"/os-simpsons-31a-temporada-episodio-21-as-detestaveis-garotinhas-de-oito-anos_eb560bad4.html"},{"id":730,"url":"/os-simpsons-31a-temporada-episodio-22-estilo-canino_3067af08c.html"},{"id":731,"url":"/os-simpsons-32a-temporada-episodio-01-burns-o-chefe-espiao_7371eb39e.html"},{"id":732,"url":"/os-simpsons-32a-temporada-episodio-02-eu-carumbus_606a5ebbd.html"},{"id":733,"url":"/os-simpsons-32a-temporada-episodio-03-historias-no-museum_5065b2f4e.html"},{"id":734,"url":"/os-simpsons-32a-temporada-episodio-04-a-casa-da-arvore-de-horror-xxxi_cb3a7e04c.html"},{"id":735,"url":"/os-simpsons-32a-temporada-episodio-05-o-pecado-bebi-ao-lado_7dd3a829e.html"},{"id":736,"url":"/os-simpsons-32a-temporada-episodio-06-noticias-de-podcast_cce7a215b.html"},{"id":737,"url":"/os-simpsons-32a-temporada-episodio-07-tres-sonhos-negados_5d876ece1.html"},{"id":738,"url":"/os-simpsons-32a-temporada-episodio-08-o-caminho-para-cincinnati_2063dc5fe.html"},{"id":739,"url":"/os-simpsons-32a-temporada-episodio-09-so-lamento_79220c3dc.html"},{"id":740,"url":"/os-simpsons-32a-temporada-episodio-10-um-natal-de-verao-em-springfield_b125e5b66.html"},{"id":741,"url":"/os-simpsons-32a-temporada-episodio-11-nasce-um-pai_7f0c7143b.html"},{"id":742,"url":"/os-simpsons-32a-temporada-episodio-12-o-diario-da-professora_b3913cce4.html"},{"id":743,"url":"/os-simpsons-32a-temporada-episodio-13-tacada-de-mestre_fa8fa66fc.html"},{"id":744,"url":"/os-simpsons-32a-temporada-episodio-14-o-heroi-rural_584488645.html"},{"id":745,"url":"/os-simpsons-32a-temporada-episodio-15-robos-de-pizzaria-sonham-com-guitarras-eletrica_8fb176655.html"},{"id":746,"url":"/os-simpsons-32a-temporada-episodio-16-um-estranho-natal_346eb39fd.html"},{"id":747,"url":"/os-simpsons-32a-temporada-episodio-17-mulheres-joias-curta_ec85651bf.html"},{"id":748,"url":"/os-simpsons-32a-temporada-episodio-18-reis-do-hamburguer_c5f851656.html"},{"id":749,"url":"/os-simpsons-32a-temporada-episodio-19-panico-nas-ruas-de-springfield_1b826dd9b.html"},{"id":750,"url":"/os-simpsons-32a-temporada-episodio-20-mae-e-filha_e7475fd6d.html"},{"id":751,"url":"/os-simpsons-32a-temporada-episodio-21-o-vovo-que-espionava_7995bbe1a.html"},{"id":752,"url":"/os-simpsons-32a-temporada-episodio-22-o-ultimo-guerreiro-do-bar_85c182a21.html"},{"id":753,"url":"/os-simpsons-33a-temporada-episodio-01-a-estrela-dos-bastidores_9984e2988.html"},{"id":754,"url":"/os-simpsons-33a-temporada-episodio-02-bart-na-cadeia_7c5b4c4f4.html"},{"id":755,"url":"/os-simpsons-33a-temporada-episodio-03-casa-da-arvore-de-horror-xxxii_49719cd75.html"},{"id":756,"url":"/os-simpsons-33a-temporada-episodio-04-nosso-moe-de-ontem_661bde79f.html"},{"id":757,"url":"/os-simpsons-33a-temporada-episodio-05-a-barriga-de-lisa_fd77940f6.html"},{"id":758,"url":"/os-simpsons-33a-temporada-episodio-0607-um-flanders-serio_a0deb2cd7.html"},{"id":759,"url":"/os-simpsons-33a-temporada-episodio-08-retrato-de-um-criado-em-chamas_06d4fcf4f.html"},{"id":760,"url":"/os-simpsons-33a-temporada-episodio-09-maes-e-outros-estranhos_1d04608bc.html"},{"id":761,"url":"/os-simpsons-33a-temporada-episodio-10-maggie-e-a-mafia_d776884dd.html"},{"id":762,"url":"/os-simpsons-33a-temporada-episodio-11-gold-marge_8cb43fbd5.html"},{"id":763,"url":"/os-simpsons-33a-temporada-episodio-12-desfocados-e-pelados_268ee623e.html"},{"id":764,"url":"/os-simpsons-33a-temporada-episodio-13-as-trilhas-na-montanha_9a82b1a7c.html"},{"id":765,"url":"/os-simpsons-33a-temporada-episodio-14-nao-vai-acreditar-sobre-o-que-e-esse-episodio-o-terceiro-bloco-vai-chocar-voce_8fbb42fe2.html"},{"id":766,"url":"/os-simpsons-33a-temporada-episodio-15-bart-o-descolado_db03004e2.html"},{"id":767,"url":"/os-simpsons-33a-temporada-episodio-16-uma-pequena-mentira_6519f2306.html"},{"id":768,"url":"/os-simpsons-33a-temporada-episodio-17-o-som-de-gengivas-sangrentas_8fa99dbda.html"},{"id":769,"url":"/os-simpsons-33a-temporada-episodio-18-meu-polvo-e-a-professora_26cb97784.html"},{"id":770,"url":"/os-simpsons-33a-temporada-episodio-19-elas-so-querem-se-divertir_93703e2fb.html"},{"id":771,"url":"/os-simpsons-33a-temporada-episodio-20-marge-a-malvada_96814e918.html"},{"id":772,"url":"/os-simpsons-33a-temporada-episodio-21-carne-e-assassinato_1b6d2192b.html"},{"id":773,"url":"/os-simpsons-33a-temporada-episodio-22-o-rock_1c27f323f.html"},{"id":774,"url":"/os-simpsons-34a-temporada-episodio-01-misterios-no-zoo_fe48722ab.html"},{"id":775,"url":"/os-simpsons-34a-temporada-episodio-02-lisa-pistola_f93f2af03.html"},{"id":776,"url":"/os-simpsons-34a-temporada-episodio-03-o-amor-esta-no-racking_b03f81450.html"},{"id":777,"url":"/os-simpsons-34a-temporada-episodio-04-o-rei-dos-bacanas_0839fe14c.html"},{"id":778,"url":"/os-simpsons-34a-temporada-episodio-05-nao-e-o-it_a9547a335.html"},{"id":779,"url":"/os-simpsons-34a-temporada-episodio-06-casa-da-arvore-de-horror-xxxiii_ab2d26045.html"},{"id":780,"url":"/musicvideo.php?vid=674af1b7c"}]